LICENSE
README.md
setup.cfg
setup.py
mqbench/__init__.py
mqbench/advanced_ptq.py
mqbench/convert_deploy.py
mqbench/custom_symbolic_opset.py
mqbench/fuser_method_mappings.py
mqbench/fusion_method.py
mqbench/observer.py
mqbench/prepare_by_platform.py
mqbench/scheme.py
mqbench/weight_equalization.py
mqbench/custom_quantizer/__init__.py
mqbench/custom_quantizer/academic_quantizer.py
mqbench/custom_quantizer/model_quantizer.py
mqbench/custom_quantizer/nlp_quantizer.py
mqbench/custom_quantizer/onnx_qnn_quantizer.py
mqbench/custom_quantizer/openvino_quantizer.py
mqbench/custom_quantizer/tengine_u8_quantizer.py
mqbench/custom_quantizer/tensorrt_quantizer.py
mqbench/custom_quantizer/total_int_quantizer.py
mqbench/custom_quantizer/vitis_quantizer.py
mqbench/deploy/__init__.py
mqbench/deploy/common.py
mqbench/deploy/convert_xir.py
mqbench/deploy/deploy_linear.py
mqbench/deploy/deploy_nnie.py
mqbench/deploy/deploy_onnx_qlinear.py
mqbench/deploy/deploy_onnx_qnn.py
mqbench/deploy/deploy_openvino.py
mqbench/deploy/deploy_stpu.py
mqbench/deploy/deploy_tengine.py
mqbench/fake_quantize/__init__.py
mqbench/fake_quantize/adaround_quantizer.py
mqbench/fake_quantize/dorefa.py
mqbench/fake_quantize/dsq.py
mqbench/fake_quantize/fixed.py
mqbench/fake_quantize/lsq.py
mqbench/fake_quantize/nnie.py
mqbench/fake_quantize/pact.py
mqbench/fake_quantize/qdrop_quantizer.py
mqbench/fake_quantize/quantize_base.py
mqbench/fake_quantize/tqt.py
mqbench/nn/__init__.py
mqbench/nn/intrinsic/__init__.py
mqbench/nn/intrinsic/modules/__init__.py
mqbench/nn/intrinsic/modules/fused.py
mqbench/nn/intrinsic/qat/__init__.py
mqbench/nn/intrinsic/qat/modules/__init__.py
mqbench/nn/intrinsic/qat/modules/conv_fused.py
mqbench/nn/intrinsic/qat/modules/deconv_fused.py
mqbench/nn/intrinsic/qat/modules/freezebn.py
mqbench/nn/intrinsic/qat/modules/linear_fused.py
mqbench/nn/modules/__init__.py
mqbench/nn/modules/freezebn.py
mqbench/nn/qat/__init__.py
mqbench/nn/qat/modules/__init__.py
mqbench/nn/qat/modules/conv.py
mqbench_torch2.egg-info/PKG-INFO
mqbench_torch2.egg-info/SOURCES.txt
mqbench_torch2.egg-info/dependency_links.txt
mqbench_torch2.egg-info/requires.txt
mqbench_torch2.egg-info/top_level.txt
