Metadata-Version: 2.1
Name: mqbench-torch2
Version: 0.1.1
Summary: model quantization tools.
Home-page: https://github.com/StephenChou0119/MQBench
Author: weiyuzhou, The Great Cold
Author-email: short_after@163.com
License: Apache-2.0
Platform: UNKNOWN
Classifier: Development Status :: 3 - Alpha
Classifier: Programming Language :: Python :: 3
Classifier: Operating System :: POSIX :: Linux
Requires-Python: >=3.10
License-File: LICENSE
